windows_fonts-1.0.0.dist-info/METADATA
windows_fonts-1.0.0.dist-info/WHEEL
windows_fonts-1.0.0.dist-info/license_files/LICENSE
windows_fonts/py.typed
windows_fonts/_windows_fonts.pyi
windows_fonts/__init__.py
windows_fonts/_windows_fonts.cp38-win_amd64.pyd
windows_fonts-1.0.0.dist-info/RECORD
