Metadata-Version: 2.1
Name: windows-fonts
Version: 1.0.0
Classifier: Programming Language :: Rust
Classifier: Programming Language :: Python :: Implementation :: CPython
Classifier: Programming Language :: Python :: Implementation :: PyPy
Classifier: Topic :: Text Processing :: Fonts
Requires-Dist: pytest >= 7; extra == 'tests'
Requires-Dist: black; extra == 'tests'
Requires-Dist: coverage; extra == 'tests'
Provides-Extra: tests
License-File: LICENSE
Summary: Query Windows fonts by name
Author-email: Ash Berlin-Taylor <ash_github@firemirror.com>
Requires-Python: >=3.7
Project-URL: Issues, https://github.com/ashb/windows-fonts/issues
Project-URL: Homepage, https://github.com/ashb/windows-fonts
